{"ENTITY_ID":12,"tables":[{"id":"69eff033-62a1-4c73-b11a-897a7e97c17a","position":{"x":583,"y":254},"data":{"table_name":"user","fields":[{"fieldName":"id","fieldType":2,"isPK":true,"isNotNull":false,"isUnique":false,"defaultValue":"","args":"","isAutoIncrement":false},{"fieldName":"username","fieldType":10,"isPK":false,"isNotNull":true,"isUnique":true,"defaultValue":"","args":["512"],"isAutoIncrement":false},{"fieldName":"email","fieldType":10,"isPK":false,"isNotNull":true,"isUnique":true,"defaultValue":"","args":["512"],"isAutoIncrement":false},{"fieldName":"password","fieldType":10,"isPK":false,"isNotNull":true,"isUnique":false,"defaultValue":"","args":["512"],"isAutoIncrement":false}],"next_id":7,"checkName":[],"checkCondition":[]}},{"id":"c1a3c014-13c3-4fb3-ba66-ecb41356c69e","position":{"x":32,"y":814},"data":{"table_name":"Publisher","fields":[{"fieldName":"id","fieldType":2,"isPK":true,"isNotNull":false,"isUnique":false,"defaultValue":"","args":"","isAutoIncrement":false}],"next_id":1,"checkName":[],"checkCondition":[]}},{"id":"2704ac05-ea07-41d8-a3f5-fb17f7597b6c","position":{"x":237,"y":501},"data":{"table_name":"Administrator","fields":[],"next_id":3,"checkName":[],"checkCondition":[]}},{"id":"61503165-67f1-42e1-a9e5-7349dde9084f","position":{"x":604,"y":512},"data":{"table_name":"Artist","fields":[{"fieldName":"artistic_name","fieldType":10,"isPK":false,"isNotNull":true,"isUnique":true,"defaultValue":"","args":["512"],"isAutoIncrement":false}],"next_id":3,"checkName":[],"checkCondition":[]}},{"id":"235b00cb-1e31-414b-a7a9-72eeba3521ea","position":{"x":980,"y":510},"data":{"table_name":"Consumer","fields":[{"fieldName":"premium","fieldType":8,"isPK":false,"isNotNull":true,"isUnique":false,"defaultValue":"","args":"","isAutoIncrement":false},{"fieldName":"address","fieldType":10,"isPK":false,"isNotNull":false,"isUnique":false,"defaultValue":"","args":["512"],"isAutoIncrement":false}],"next_id":5,"checkName":[],"checkCondition":[]}},{"id":"fb2605e0-b94f-4322-b30f-ef37c324db07","position":{"x":921,"y":631},"data":{"table_name":"playlist","fields":[{"fieldName":"id","fieldType":2,"isPK":true,"isNotNull":false,"isUnique":false,"defaultValue":"","args":"","isAutoIncrement":false},{"fieldName":"isPrivate","fieldType":0,"isPK":false,"isNotNull":false,"isUnique":false,"defaultValue":"","args":[1,1],"isAutoIncrement":false}],"next_id":2,"checkName":[],"checkCondition":[]}},{"id":"021468a1-ff7d-4501-8574-975b7a76f0b7","position":{"x":176,"y":596},"data":{"table_name":"Song","fields":[{"fieldName":"id","fieldType":2,"isPK":true,"isNotNull":false,"isUnique":false,"defaultValue":"","args":"","isAutoIncrement":false},{"fieldName":"name","fieldType":10,"isPK":true,"isNotNull":false,"isUnique":false,"defaultValue":"","args":["512"],"isAutoIncrement":false},{"fieldName":"release_date","fieldType":8,"isPK":false,"isNotNull":true,"isUnique":false,"defaultValue":"","args":"","isAutoIncrement":false}],"next_id":4,"checkName":[],"checkCondition":[]}},{"id":"35e8e1a6-0210-488a-b777-4f1ade1b8b0f","position":{"x":534,"y":697},"data":{"table_name":"Card","fields":[{"fieldName":"field_0","fieldType":3,"isPK":true,"isNotNull":false,"isUnique":false,"defaultValue":"","args":[1,1],"isAutoIncrement":false}],"next_id":1,"checkName":[],"checkCondition":[]}},{"id":"2d3603fa-8b50-4a74-9338-3ddf735f367e","position":{"x":119,"y":306},"data":{"table_name":"Album","fields":[{"fieldName":"field_0","fieldType":3,"isPK":true,"isNotNull":false,"isUnique":false,"defaultValue":"","args":[1,1],"isAutoIncrement":false}],"next_id":1,"checkName":[],"checkCondition":[]}},{"id":"c13d924f-733d-41b5-a845-b9ea67aab528","position":{"x":1032,"y":202},"data":{"table_name":"Top10","fields":[{"fieldName":"field_0","fieldType":3,"isPK":true,"isNotNull":false,"isUnique":false,"defaultValue":"","args":[1,1],"isAutoIncrement":false}],"next_id":1,"checkName":[],"checkCondition":[]}},{"id":"b1143335-fd9e-462f-8c86-d3fdaa9edbfb","position":{"x":1280,"y":308},"data":{"table_name":"Subscripton","fields":[{"fieldName":"id","fieldType":2,"isPK":true,"isNotNull":false,"isUnique":false,"defaultValue":"","args":"","isAutoIncrement":true},{"fieldName":"begin","fieldType":8,"isPK":false,"isNotNull":false,"isUnique":false,"defaultValue":"","args":"","isAutoIncrement":false},{"fieldName":"end","fieldType":8,"isPK":false,"isNotNull":false,"isUnique":false,"defaultValue":"","args":"","isAutoIncrement":false}],"next_id":3,"checkName":[],"checkCondition":[]}},{"id":"ebc017e2-c653-4250-9677-a2603eca7803","position":{"x":971,"y":753},"data":{"table_name":"comment","fields":[{"fieldName":"id","fieldType":2,"isPK":true,"isNotNull":false,"isUnique":false,"defaultValue":"","args":"","isAutoIncrement":true},{"fieldName":"body","fieldType":11,"isPK":false,"isNotNull":false,"isUnique":false,"defaultValue":"","args":["512"],"isAutoIncrement":false},{"fieldName":"tempo","fieldType":8,"isPK":false,"isNotNull":false,"isUnique":false,"defaultValue":"","args":"","isAutoIncrement":false}],"next_id":3,"checkName":[],"checkCondition":[]}}],"links":[{"source":"61503165-67f1-42e1-a9e5-7349dde9084f","target":"69eff033-62a1-4c73-b11a-897a7e97c17a","order":"parenting","sourceCard":"0:1","targetCard":"0:1","label":"complete","hierType":"complete","sourceisweak":false,"targetisweak":false},{"source":"2704ac05-ea07-41d8-a3f5-fb17f7597b6c","target":"69eff033-62a1-4c73-b11a-897a7e97c17a","order":"parenting","sourceCard":"0:1","targetCard":"0:1","label":"complete","hierType":"complete","sourceisweak":false,"targetisweak":false},{"source":"235b00cb-1e31-414b-a7a9-72eeba3521ea","target":"69eff033-62a1-4c73-b11a-897a7e97c17a","order":"parenting","sourceCard":"0:1","targetCard":"0:1","label":"complete","hierType":"complete","sourceisweak":false,"targetisweak":false},{"source":"c1a3c014-13c3-4fb3-ba66-ecb41356c69e","target":"021468a1-ff7d-4501-8574-975b7a76f0b7","order":"normal","sourceCard":"0:1","targetCard":"0:1","label":"publica","hierType":null,"sourceisweak":false,"targetisweak":false},{"source":"b1143335-fd9e-462f-8c86-d3fdaa9edbfb","target":"235b00cb-1e31-414b-a7a9-72eeba3521ea","order":"normal","sourceCard":"0:1","targetCard":"0:1","label":"subscreve","hierType":null,"sourceisweak":false,"targetisweak":false}],"normalization":1,"database":0}